{"1":[{"ar":"إِنَّآ","ur":"بےشک ہم نے","hi":"बेशक हमने","ro":"bayshak ham","rt":""},{"ar":"أَعۡطَيۡنَٰكَ","ur":"عطا کی ہم نے آپ کو","hi":"अता किया हमने आपको","ro":"ataa ki ham nay aap ko","rt":"ع ط و"},{"ar":"ٱلۡكَوۡثَرَ","ur":"کوثر","hi":"कौसर","ro":"kawsar","rt":"ک ث ر"}],"2":[{"ar":"فَصَلِّ","ur":"پس نماز پڑھیے","hi":"पस नमाज़ पढ़िए","ro":"pas namaz parrhiay","rt":"ص ل و"},{"ar":"لِرَبِّكَ","ur":"اپنے رب کے لیے","hi":"अपने रब के लिए","ro":"apnay Rabb kay liay","rt":""},{"ar":"وَٱنۡحَرۡ","ur":"اور قربانی کیجیے","hi":"और क़ुर्बानी कीजिए","ro":"awr qurbani kijiay","rt":"ن ح ر"}],"3":[{"ar":"إِنَّ","ur":"بےشک","hi":"बेशक","ro":"bayshak","rt":""},{"ar":"شَانِئَكَ","ur":"دشمن آپ کا","hi":"दुश्मन आपका","ro":"dushman aap ka","rt":"ش أ ن"},{"ar":"هُوَ","ur":"وہی","hi":"वो ही","ro":"wohi","rt":""},{"ar":"ٱلۡأَبۡتَرُ","ur":"جڑ کٹا ہے","hi":"जड़ कटा है","ro":"jarr kata hay","rt":"ب ت ر"}]}