{"1":[{"ar":"قُلۡ","ur":"کہہ دیجیے","hi":"कह दीजिए","ro":"keh dijiay","rt":""},{"ar":"أُوحِيَ","ur":"وحی کی گئی","hi":"वही की गई","ro":"wahi ki gai","rt":""},{"ar":"إِلَيَّ","ur":"میری طرف","hi":"मेरी तरफ़","ro":"meri taraf","rt":""},{"ar":"أَنَّهُ","ur":"بےشک وہ","hi":"बेशक वो","ro":"bayshak woh","rt":""},{"ar":"ٱسۡتَمَعَ","ur":"غور سے سنا","hi":"ग़ौर से सुना","ro":"ghawr say suna","rt":""},{"ar":"نَفَرٌ","ur":"ایک گروہ نے","hi":"एक गिरोह ने","ro":"aik goroh nay","rt":"ن ف ر"},{"ar":"مِّنَ ٱلۡجِنِّ","ur":"جنوں میں سے","hi":"जिन्नों में से","ro":"jinnon mein say","rt":""},{"ar":"فَقَالُوٓاْ","ur":"تو انہوں نے کہا","hi":"तो उन्होंने कहा","ro":"to unhon nay kaha","rt":""},{"ar":"إِنَّا","ur":"بےشک ہم","hi":"बेशक हम","ro":"bayshak ham","rt":""},{"ar":"سَمِعۡنَا","ur":"سنا ہم نے","hi":"सुना हमने","ro":"suna ham nay","rt":""},{"ar":"قُرۡءَانًا","ur":"قرآن","hi":"क़ुरआन","ro":"Qur’an","rt":""},{"ar":"عَجَبًا","ur":"عجیب","hi":"अजीब","ro":"ajeeb","rt":"ع ج ب"}],"2":[{"ar":"يَهۡدِيٓ","ur":"وہ راہ نمائی کرتا ہے","hi":"वो रहनुमाई करता है","ro":"woh rahnumai karta hay","rt":""},{"ar":"إِلَى ٱلرُّشۡدِ","ur":"طرف بھلائی کے","hi":"तरफ़ भलाई के","ro":"taraf bhalai kay","rt":"ر ش د"},{"ar":"فَـَٔامَنَّا","ur":"پس ایمان لائے ہم","hi":"पस ईमान लाए हम","ro":"pas iman la’ay ham","rt":""},{"ar":"بِهِۦۖ","ur":"اس پر","hi":"उस पर","ro":"is par","rt":""},{"ar":"وَلَن","ur":"اور ہر گز نہیں","hi":"और हरगिज़ नहीं","ro":"awr hargiz nahin","rt":""},{"ar":"نُّشۡرِكَ","ur":"ہم شریک کریں گے","hi":"हम शरीक करेंगे","ro":"ham sharik karein gay","rt":"ش ر ک"},{"ar":"بِرَبِّنَآ","ur":"ساتھ اپنے رب کے","hi":"साथ अपने रब के","ro":"sath apnay Rabb kay","rt":""},{"ar":"أَحَدًا","ur":"کسی ایک کو","hi":"किसी एक को","ro":"kisi aik ko","rt":""}],"3":[{"ar":"وَأَنَّهُۥ","ur":"اور یہ کہ","hi":"और ये कि","ro":"awr yeh keh","rt":""},{"ar":"تَعَٰلَىٰ","ur":"بہت بلند ہے","hi":"बहुत बुलन्द है","ro":"bahot buland hay","rt":""},{"ar":"جَدُّ","ur":"شان","hi":"शान","ro":"shaan","rt":""},{"ar":"رَبِّنَا","ur":"ہمارے رب کی","hi":"हमारे रब की","ro":"hamaray Rabb ki","rt":""},{"ar":"مَا","ur":"نہیں","hi":"नहीं","ro":"nahin","rt":""},{"ar":"ٱتَّخَذَ","ur":"بنائی اس نے","hi":"बनाई उसने","ro":"banai us nay","rt":""},{"ar":"صَٰحِبَةً","ur":"کوئی بیوی","hi":"कोई बीवी","ro":"koi biwi","rt":""},{"ar":"وَلَا","ur":"اور نہ","hi":"और ना","ro":"awr nah","rt":""},{"ar":"وَلَدًا","ur":"کوئی اولاد","hi":"कोई औलाद","ro":"koi awlad","rt":""}],"4":[{"ar":"وَأَنَّهُۥ","ur":"اور یہ کہ وہ","hi":"और ये कि","ro":"awr yeh keh woh","rt":""},{"ar":"كَانَ","ur":"تھے","hi":"थे","ro":"thay","rt":""},{"ar":"يَقُولُ","ur":"کہا کرتے","hi":"कहा करते","ro":"kaha kartay","rt":""},{"ar":"سَفِيهُنَا","ur":"بے وقوف ہمارے","hi":"बेवक़ूफ़ हमारे","ro":"bay waquf hamaray","rt":"س ف ہ"},{"ar":"عَلَى ٱللَّهِ","ur":"اللہ پر","hi":"अल्लाह पर","ro":"Allah par","rt":""},{"ar":"شَطَطًا","ur":"زیادتی کی باتیں","hi":"ज़्यादती की बातें","ro":"ziyadati ki baatein","rt":"ش ط ط"}],"5":[{"ar":"وَأَنَّا","ur":"اور بےشک ہم","hi":"और बेशक हम","ro":"awr bayshak ham","rt":""},{"ar":"ظَنَنَّآ","ur":"گمان کیا ہم نے","hi":"गुमान किया हमने","ro":"guman kiya ham nay","rt":""},{"ar":"أَن","ur":"کہ","hi":"कि","ro":"keh","rt":""},{"ar":"لَّن","ur":"ہرگز نہیں","hi":"हरगिज़ नहीं","ro":"harqiz nahin","rt":""},{"ar":"تَقُولَ","ur":"کہیں گے","hi":"कहेंगे","ro":"kahein gay","rt":""},{"ar":"ٱلۡإِنسُ","ur":"انسان","hi":"इन्सान","ro":"insan","rt":""},{"ar":"وَٱلۡجِنُّ","ur":"اور جن","hi":"और जिन्न","ro":"awr jinn","rt":""},{"ar":"عَلَى ٱللَّهِ","ur":"اللہ پر","hi":"अल्लाह पर","ro":"Allah par","rt":""},{"ar":"كَذِبًا","ur":"کوئی جھوٹ","hi":"कोई झूठ","ro":"koi jhoot","rt":""}],"6":[{"ar":"وَأَنَّهُۥ","ur":"اور بےشک وہ","hi":"और बेशक वो","ro":"awr bayshak woh","rt":""},{"ar":"كَانَ","ur":"تھے","hi":"थे","ro":"thay","rt":""},{"ar":"رِجَالٌ","ur":"کچھ لوگ","hi":"कुछ लोग","ro":"kuchh log","rt":""},{"ar":"مِّنَ ٱلۡإِنسِ","ur":"انسانوں میں سے","hi":"इन्सानों में से","ro":"insanon mein say","rt":""},{"ar":"يَعُوذُونَ","ur":"جو پناہ لیتے تھے","hi":"जो पनाह लेते थे","ro":"jo panah letay thay","rt":"ع و ذ"},{"ar":"بِرِجَالٍ","ur":"کچھ لوگوں کی","hi":"कुछ लोगों की","ro":"kuchh logon ki","rt":""},{"ar":"مِّنَ ٱلۡجِنِّ","ur":"جنوں میں سے","hi":"जिन्नों में से","ro":"jinnon mein say","rt":""},{"ar":"فَزَادُوهُمۡ","ur":"توانہوں نے زیادہ کردیا انہیں","hi":"तो उन्होंने ज़्यादा कर दिया उन्हें","ro":"to unhon nay ziyadah kar diya unhein","rt":"ز ی د"},{"ar":"رَهَقًا","ur":"سرکشی میں","hi":"सरकशी में","ro":"sarkashi mein","rt":"ر ہ ق"}],"7":[{"ar":"وَأَنَّهُمۡ","ur":"اور یہ کہ وہ","hi":"और ये कि वो","ro":"awr yeh keh woh","rt":""},{"ar":"ظَنُّواْ","ur":"وہ سمجھتے تھے","hi":"वो समझते थे","ro":"woh samajh tay thay","rt":""},{"ar":"كَمَا","ur":"جیسا کہ","hi":"जैसा कि","ro":"jaisa keh","rt":""},{"ar":"ظَنَنتُمۡ","ur":"سمجھا تم نے","hi":"समझा हमने","ro":"samjha tum nay","rt":""},{"ar":"أَن","ur":"کہ","hi":"कि","ro":"keh","rt":""},{"ar":"لَّن","ur":"ہر گز نہیں","hi":"हरगिज़ नहीं","ro":"harqiz nahin","rt":""},{"ar":"يَبۡعَثَ","ur":"بھیجے گا","hi":"भेजेगा","ro":"bhejay ga","rt":""},{"ar":"ٱللَّهُ","ur":"اللہ","hi":"अल्लाह","ro":"Allah","rt":""},{"ar":"أَحَدًا","ur":"کسی ایک کو","hi":"किसी एक को","ro":"kisi aik ko","rt":""}],"8":[{"ar":"وَأَنَّا","ur":"اور بےشک ہم","hi":"और बेशक हम","ro":"awr bayshak ham","rt":""},{"ar":"لَمَسۡنَا","ur":"چھوا ہم نے","hi":"छुआ हमने","ro":"chhu’a ham nay","rt":"ل م س"},{"ar":"ٱلسَّمَآءَ","ur":"آسمان کو","hi":"आसमान को","ro":"aasman ko","rt":""},{"ar":"فَوَجَدۡنَٰهَا","ur":"تو پایا ہم نے اسے","hi":"तो पाया हमने उसे","ro":"to paya ham nay usay","rt":""},{"ar":"مُلِئَتۡ","ur":"بھرا ہوا ہے","hi":"भरा हुआ है","ro":"bhara hua hay","rt":"م ل أ"},{"ar":"حَرَسًا","ur":"پہرے داروں سے","hi":"पहरेदारों से","ro":"pehray daron say","rt":"ح ر س"},{"ar":"شَدِيدًا","ur":"سخت","hi":"सख़्त","ro":"sakht","rt":""},{"ar":"وَشُهُبًا","ur":"اور شعلوں سے","hi":"और शोलों से","ro":"awr sho’lon say","rt":"ش ہ ب"}],"9":[{"ar":"وَأَنَّا","ur":"اور بےشک ہم","hi":"और बेशक हम","ro":"awr bayshak ham","rt":""},{"ar":"كُنَّا","ur":"تھے ہم","hi":"थे हम","ro":"thay ham","rt":""},{"ar":"نَقۡعُدُ","ur":"ہم بیٹھتے","hi":"हम बैठते","ro":"ham bethty","rt":""},{"ar":"مِنۡهَا","ur":"اس کی","hi":"उसकी","ro":"us ki","rt":""},{"ar":"مَقَٰعِدَ","ur":"بیٹھنے کی جگہوں پر","hi":"बैठने की जगहों पर","ro":"bethnay ki jaghon par","rt":"ق ع د"},{"ar":"لِلسَّمۡعِۖ","ur":"سننے کے لیے","hi":"सुनने के लिए","ro":"sunnay kay lay","rt":""},{"ar":"فَمَن","ur":"تو جو کوئی","hi":"तो जो कोई","ro":"to jo koi","rt":""},{"ar":"يَسۡتَمِعِ","ur":"غور سے سنتا ہے","hi":"ग़ौर से सुनता है","ro":"ghawr say sunta hay","rt":""},{"ar":"ٱلۡأٓنَ","ur":"اب","hi":"अब","ro":"ab","rt":""},{"ar":"يَجِدۡ","ur":"وہ پاتا ہے","hi":"वो पाता है","ro":"woh pata hay","rt":""},{"ar":"لَهُۥ","ur":"اپنے لیے","hi":"अपने लिए","ro":"apnay liay","rt":""},{"ar":"شِهَابًا","ur":"ایک شعلہ","hi":"एक शोला","ro":"aik sho’la","rt":"ش ہ ب"},{"ar":"رَّصَدًا","ur":"گھات میں","hi":"घात में","ro":"ghaat mein","rt":"ر ص د"}],"10":[{"ar":"وَأَنَّا","ur":"اور بےشک ہم","hi":"औक बेशक हम","ro":"awr bayshak ham","rt":""},{"ar":"لَا نَدۡرِيٓ","ur":"نہیں ہم جانتے","hi":"नहीं हम जानते","ro":"nahin ham jantay","rt":""},{"ar":"أَشَرٌّ","ur":"کیا شر/ برائی کا","hi":"क्या शर/ बुराई का","ro":"keya shar/burai ka","rt":"ش ر ر"},{"ar":"أُرِيدَ","ur":"ارادہ کیا گیا","hi":"इरादा किया गया","ro":"iradah kiya gaya","rt":""},{"ar":"بِمَن","ur":"ساتھ ان کے جو","hi":"साथ उनके जो","ro":"sath un kay jo","rt":""},{"ar":"فِي ٱلۡأَرۡضِ","ur":"زمین میں ہیں","hi":"ज़मीन में हैं","ro":"zamin mein hain","rt":""},{"ar":"أَمۡ","ur":"یا","hi":"या","ro":"ya","rt":""},{"ar":"أَرَادَ","ur":"ارادہ کیا","hi":"इरादा किया","ro":"iradah kiya","rt":""},{"ar":"بِهِمۡ","ur":"ساتھ ان کے","hi":"साथ उनके","ro":"sath in kay","rt":""},{"ar":"رَبُّهُمۡ","ur":"ان کے رب نے","hi":"उनके रब ने","ro":"in kay Rabb nay","rt":""},{"ar":"رَشَدًا","ur":"خیر / بھلائی کا","hi":"ख़ैर/भलाई का","ro":"khair/bhalai ka","rt":"ر ش د"}],"11":[{"ar":"وَأَنَّا","ur":"اور بےشک ہم","hi":"और बेशक हम","ro":"awr bayshak ham","rt":""},{"ar":"مِنَّا","ur":"ہم میں سے","hi":"हम में से","ro":"ham mein say","rt":""},{"ar":"ٱلصَّٰلِحُونَ","ur":"نیک ہیں","hi":"नेक हैं","ro":"nek hain","rt":""},{"ar":"وَمِنَّا","ur":"اور ہم میں سے","hi":"और हम में से","ro":"awr ham mein say","rt":""},{"ar":"دُونَ","ur":"علاوہ ہیں","hi":"अलावा हैं","ro":"ilawah hain","rt":""},{"ar":"ذَٰلِكَۖ","ur":"اس کے","hi":"उसके","ro":"is kay","rt":""},{"ar":"كُنَّا","ur":"ہیں ہم","hi":"हैं हम","ro":"hain ham","rt":""},{"ar":"طَرَآئِقَ","ur":"طریقوں پر","hi":"तरीक़ों पर","ro":"tariqon par","rt":"ط ر ق"},{"ar":"قِدَدًا","ur":"مختلف","hi":"मुख़्तलिफ़","ro":"mukhtalif","rt":"ق د د"}],"12":[{"ar":"وَأَنَّا","ur":"اور بےشک ہم","hi":"और बेशक हम","ro":"awr bayshak ham","rt":""},{"ar":"ظَنَنَّآ","ur":"یقین رکھتے ہیں ہم","hi":"यक़ीन रखते हैं हम","ro":"yaqin rakhtay hain ham","rt":""},{"ar":"أَن","ur":"کہ","hi":"कि","ro":"keh","rt":""},{"ar":"لَّن","ur":"ہر گز نہیں","hi":"हरगिज़ नहीं","ro":"harqiz nahin","rt":""},{"ar":"نُّعۡجِزَ","ur":"ہم عاجز کرسکتے","hi":"हम आजिज़ कर सकते","ro":"ham aajiz kar saktay","rt":""},{"ar":"ٱللَّهَ","ur":"اللہ کو","hi":"अल्लाह को","ro":"Allah ko","rt":""},{"ar":"فِي ٱلۡأَرۡضِ","ur":"زمین میں","hi":"ज़मीन में","ro":"zamin mein","rt":""},{"ar":"وَلَن","ur":"اور ہرگز نہیں","hi":"और हरगिज़ नहीं","ro":"awr hargiz nahin","rt":""},{"ar":"نُّعۡجِزَهُۥ","ur":"ہم عاجز کرسکتے اسے","hi":"हम आजिज़ कर सकते उसे","ro":"ham aajiz kar saktay usay","rt":""},{"ar":"هَرَبًا","ur":"بھاگ کر","hi":"भाग कर","ro":"bhaag kar","rt":"ہ ر ب"}],"13":[{"ar":"وَأَنَّا","ur":"اور بےشک ہم نے","hi":"और बेशक हमने","ro":"awr bayshak ham","rt":""},{"ar":"لَمَّا","ur":"جب","hi":"जब","ro":"jab","rt":""},{"ar":"سَمِعۡنَا","ur":"سنا ہم نے","hi":"सुना हमने","ro":"suna ham nay","rt":""},{"ar":"ٱلۡهُدَىٰٓ","ur":"ہدایت کو","hi":"हिदायत को","ro":"hidayat ko","rt":""},{"ar":"ءَامَنَّا","ur":"ایمان لے آئے ہم","hi":"ईमान ले आए हम","ro":"iman lay aa’ay ham","rt":""},{"ar":"بِهِۦۖ","ur":"اس پر","hi":"उस पर","ro":"us par","rt":""},{"ar":"فَمَن","ur":"پس جو کوئی","hi":"पस जो कोई","ro":"pas jo koi","rt":""},{"ar":"يُؤۡمِنۢ","ur":"ایمان لائے گا","hi":"ईमान लाएगा","ro":"iman la’ay ga","rt":""},{"ar":"بِرَبِّهِۦ","ur":"اپنے رب پر","hi":"अपने रब पर","ro":"apnay Rabb par","rt":""},{"ar":"فَلَا","ur":"تو نہ","hi":"तो ना","ro":"to nah","rt":""},{"ar":"يَخَافُ","ur":"وہ ڈرے گا","hi":"वो डरेगा","ro":"woh daray ga","rt":""},{"ar":"بَخۡسًا","ur":"کسی کمی سے","hi":"किसी कमी से","ro":"kisi kami say","rt":"ب خ س"},{"ar":"وَلَا","ur":"اور نہ","hi":"और ना","ro":"awr nah","rt":""},{"ar":"رَهَقًا","ur":"کسی زیادتی سے","hi":"किसी ज़्यादती से","ro":"kisi ziyadti say","rt":"ر ہ ق"}],"14":[{"ar":"وَأَنَّا","ur":"اور بےشک ہم","hi":"और बेशक हम","ro":"awr bayshak ham","rt":""},{"ar":"مِنَّا","ur":"ہم میں سے کچھ","hi":"हम में से कुछ","ro":"ham mein say kuchh","rt":""},{"ar":"ٱلۡمُسۡلِمُونَ","ur":"مسلمان ہیں","hi":"मुसलमान हैं","ro":"musalman hain","rt":""},{"ar":"وَمِنَّا","ur":"اور ہم میں سے کچھ","hi":"और हम में से कुछ","ro":"awr ham mein say kuchh","rt":""},{"ar":"ٱلۡقَٰسِطُونَۖ","ur":"ظالم ہیں","hi":"ज़ालिम हैं","ro":"zalim hain","rt":"ق س ط"},{"ar":"فَمَنۡ","ur":"تو جو کوئی","hi":"तो जो कोई","ro":"to jo koi","rt":""},{"ar":"أَسۡلَمَ","ur":"فرماں بردار ہوگیا","hi":"फ़रमाबरदार हो गया","ro":"arman bardar ho gaya","rt":""},{"ar":"فَأُوْلَٰٓئِكَ","ur":"تو یہی لوگ ہیں","hi":"तो यही लोग हैं","ro":"to yehi log hain","rt":""},{"ar":"تَحَرَّوۡاْ","ur":"جنہوں نے ارادہ کیا","hi":"जिन्होंने इरादा किया","ro":"jinhon nay iradah kiya","rt":"ح ر ر"},{"ar":"رَشَدًا","ur":"بھلائی کا","hi":"भलाई का","ro":"bhalai ka","rt":""}],"15":[{"ar":"وَأَمَّا","ur":"اور رہے","hi":"और रहे","ro":"awr rahay","rt":""},{"ar":"ٱلۡقَٰسِطُونَ","ur":"ظالم لوگ","hi":"ज़ालिम लोग","ro":"zalim log","rt":""},{"ar":"فَكَانُواْ","ur":"تو ہیں وہ","hi":"तो हैं वो","ro":"to hain woh","rt":""},{"ar":"لِجَهَنَّمَ","ur":"جہنم کا","hi":"जहन्नम का","ro":"jahannam ka","rt":""},{"ar":"حَطَبًا","ur":"ایندھن","hi":"ईंधन","ro":"eendhan","rt":"ح ط ب"}],"16":[{"ar":"وَّأَنۡ","ur":"اور یہ کہ","hi":"और ये कि","ro":"awr yeh keh","rt":""},{"ar":"لَّوِ","ur":"اگر","hi":"अगर","ro":"agar","rt":""},{"ar":"ٱسۡتَقَٰمُواْ","ur":"وہ قائم ہوجاتے","hi":"वो क़ायम हो जाते","ro":"woh qa’im ho jatay","rt":"ق و م"},{"ar":"عَلَى ٱلطَّرِيقَةِ","ur":"راستے پر","hi":"रास्ते पर","ro":"rastay par","rt":"ط ر ق"},{"ar":"لَأَسۡقَيۡنَٰهُم","ur":"البتہ پلاتے ہم انہیں","hi":"अलबत्ता पिलाते हम उन्हें","ro":"albattah pilatay ham unhein","rt":"س ق ی"},{"ar":"مَّآءً","ur":"پانی","hi":"पानी","ro":"pani","rt":""},{"ar":"غَدَقًا","ur":"وافر","hi":"वाफ़र","ro":"wafir","rt":"غ د ق"}],"17":[{"ar":"لِّنَفۡتِنَهُمۡ","ur":"تاکہ ہم آزمائش کریں ان کی","hi":"ताकि हम आज़माऐं उन्हें","ro":"takeh ham aazma’ish karein un ki","rt":"ف ت ن"},{"ar":"فِيهِۚ","ur":"اس میں","hi":"उसमें","ro":"is mein","rt":""},{"ar":"وَمَن","ur":"اور جو کوئی","hi":"और जो कोई","ro":"awr jo koi","rt":""},{"ar":"يُعۡرِضۡ","ur":"اعراض کرے گا","hi":"ऐराज़ करेगा","ro":"i’raz karay ga","rt":""},{"ar":"عَن ذِكۡرِ","ur":"ذکر سے","hi":"ज़िक्र से","ro":"zikr say","rt":""},{"ar":"رَبِّهِۦ","ur":"اپنے رب کے","hi":"अपने रब के","ro":"apnay Rabb kay","rt":""},{"ar":"يَسۡلُكۡهُ","ur":"وہ داخل کرے گا اسے","hi":"वो दाख़िल करेगा उसे","ro":"woh dakhil karay ga usay","rt":"س ل ک"},{"ar":"عَذَابًا","ur":"عذاب میں","hi":"अज़ाब में","ro":"azab mein","rt":""},{"ar":"صَعَدًا","ur":"سخت","hi":"सख़्त","ro":"sakht","rt":"ص ع د"}],"18":[{"ar":"وَأَنَّ","ur":"اور بےشک","hi":"और बेशक","ro":"awr bayshak","rt":""},{"ar":"ٱلۡمَسَٰجِدَ","ur":"مسجدیں","hi":"मस्जिदें","ro":"masjidein","rt":""},{"ar":"لِلَّهِ","ur":"اللہ کے لیے ہیں","hi":"अल्लाह के लिए हैं","ro":"Allah kay liay hain","rt":""},{"ar":"فَلَا","ur":"پس نہ","hi":"पस ना","ro":"pas nah","rt":""},{"ar":"تَدۡعُواْ","ur":"تم پکارو","hi":"तुम पुकारो","ro":"tum pukaro","rt":""},{"ar":"مَعَ","ur":"ساتھ","hi":"साथ","ro":"sath","rt":""},{"ar":"ٱللَّهِ","ur":"اللہ کے","hi":"अल्लाह के","ro":"Allah kay","rt":""},{"ar":"أَحَدًا","ur":"کسی ایک کو","hi":"किसी  एक को","ro":"kisi aik ko","rt":""}],"19":[{"ar":"وَأَنَّهُۥ","ur":"اور بےشک وہ","hi":"और बेशक वो","ro":"awr bayshak woh","rt":""},{"ar":"لَمَّا","ur":"جب","hi":"जब","ro":"jab","rt":""},{"ar":"قَامَ","ur":"کھڑا ہوا","hi":"खड़ा हुआ","ro":"kharra hua","rt":""},{"ar":"عَبۡدُ","ur":"بندہ","hi":"बन्दा","ro":"bandah","rt":""},{"ar":"ٱللَّهِ","ur":"اللہ کا","hi":"अल्लाह का","ro":"Allah ka","rt":""},{"ar":"يَدۡعُوهُ","ur":"کہ وہ پکارے اسے","hi":"कि वो पुकारे उसे","ro":"keh woh pukaray usay","rt":""},{"ar":"كَادُواْ","ur":"قریب تھے وہ","hi":"क़रीब थे वो","ro":"qarib thay woh","rt":""},{"ar":"يَكُونُونَ","ur":"کہ وہ ہو جائیں","hi":"कि वो हो जाऐं","ro":"keh woh ho ja’ein","rt":""},{"ar":"عَلَيۡهِ","ur":"اس پر","hi":"उस पर","ro":"us par","rt":""},{"ar":"لِبَدًا","ur":"گروہ درگروہ (حملہ آور)","hi":"गिरोह दर गिरोह(हमला आवर)","ro":"goroh dar goroh (hamlah aawar)","rt":"ل ب د"}],"20":[{"ar":"قُلۡ","ur":"کہہ دیجیے","hi":"कह दीजिए","ro":"keh dijiay","rt":""},{"ar":"إِنَّمَآ","ur":"بےشک","hi":"बेशक","ro":"bayshak","rt":""},{"ar":"أَدۡعُواْ","ur":"میں پکارتا ہوں","hi":"मैं पुकारता हूँ","ro":"main pukarta hun","rt":""},{"ar":"رَبِّي","ur":"اپنے رب کو","hi":"अपने रब को","ro":"apnay Rabb ko","rt":""},{"ar":"وَلَآ","ur":"اور نہیں","hi":"और नहीं","ro":"awr nahin","rt":""},{"ar":"أُشۡرِكُ","ur":"میں شریک ٹہراتا","hi":"मैं शरीक ठहराता","ro":"main sharik thahrata","rt":""},{"ar":"بِهِۦٓ","ur":"ساتھ اس کے","hi":"साथ उसके","ro":"sath us kay","rt":""},{"ar":"أَحَدًا","ur":"کسی ایک کو","hi":"किसी एक को","ro":"kisi aik ko","rt":""}],"21":[{"ar":"قُلۡ","ur":"کہہ دیجیے","hi":"कह दीजिए","ro":"keh dijiay","rt":""},{"ar":"إِنِّي","ur":"بےشک میں","hi":"बेशक मैं","ro":"bayshak main","rt":""},{"ar":"لَآ أَمۡلِكُ","ur":"نہیں میں مالک ہوسکتا","hi":"नहीं मैं मालिक हो सकता","ro":"nahin main malik ho sakta","rt":""},{"ar":"لَكُمۡ","ur":"تمہارے لیے","hi":"तुम्हारे लिए","ro":"tumharay liay","rt":""},{"ar":"ضَرًّا","ur":"کسی نقصان کا","hi":"किसी नुक़्सान का","ro":"kisi nuqsan ka","rt":""},{"ar":"وَلَا","ur":"اور نہ","hi":"और ना","ro":"awr nah","rt":""},{"ar":"رَشَدًا","ur":"کسی بھلائی کا","hi":"किसी भलाई का","ro":"kisi bhalai ka","rt":""}],"22":[{"ar":"قُلۡ","ur":"کہہ دیجیے","hi":"कह दीजिए","ro":"keh dijiay","rt":""},{"ar":"إِنِّي","ur":"بےشک میں","hi":"बेशक","ro":"bayshak main","rt":""},{"ar":"لَن","ur":"ہرگز نہ","hi":"हरगिज़ ना","ro":"hargiz nah","rt":""},{"ar":"يُجِيرَنِي","ur":"پناہ دے گا مجھے","hi":"पनाह देगा मुझे","ro":"panah day ga mujhay","rt":"ج و ر"},{"ar":"مِنَ ٱللَّهِ","ur":"اللہ سے","hi":"अल्लाह से","ro":"Allah say","rt":""},{"ar":"أَحَدٌ","ur":"کوئی ایک","hi":"कोई एक","ro":"koi aik","rt":""},{"ar":"وَلَنۡ","ur":"اور ہر گز نہ","hi":"और हरगिज़ ना","ro":"awr hargiz nah","rt":""},{"ar":"أَجِدَ","ur":"میں پاؤں گا","hi":"मैं पाऊँगा","ro":"main pa’un ga","rt":""},{"ar":"مِن دُونِهِۦ","ur":"اس کے سوا","hi":"उसके सिवा","ro":"us kay siwa","rt":""},{"ar":"مُلۡتَحَدًا","ur":"کوئی جائے پناہ","hi":"कोई जाएपनाह","ro":"koi ja’ay panah","rt":"ل ح د"}],"23":[{"ar":"إِلَّا","ur":"مگر","hi":"मगर","ro":"magar","rt":""},{"ar":"بَلَٰغًا","ur":"پہنچا دینا ہے","hi":"पहुँचा देना है","ro":"pahoncha dena hay","rt":""},{"ar":"مِّنَ ٱللَّهِ","ur":"اللہ کی طرف سے (حکم)","hi":"अल्लाह की तरफ़ से (हुक्म)","ro":"Allah ki taraf say (hukm)","rt":""},{"ar":"وَرِسَٰلَٰتِهِۦۚ","ur":"اور اس کے پیغامات","hi":"और उसके पैग़ामात","ro":"awr us kay paegamaat","rt":""},{"ar":"وَمَن","ur":"اور جو کوئی","hi":"और जो कोई","ro":"awr jo koi","rt":""},{"ar":"يَعۡصِ","ur":"نافرمانی کرے گا","hi":"नाफ़रमानी करेगा","ro":"na farmani karay ga","rt":""},{"ar":"ٱللَّهَ","ur":"اللہ کی","hi":"अल्लाह की","ro":"Allah ki","rt":""},{"ar":"وَرَسُولَهُۥ","ur":"اور اس کے رسول کی","hi":"और उसके रसूल की","ro":"awr us kay Rasul ki","rt":""},{"ar":"فَإِنَّ","ur":"تو بےشک","hi":"तो बेशक","ro":"to bayshak","rt":""},{"ar":"لَهُۥ","ur":"اس کے لیے","hi":"उसके लिए","ro":"us kay liay","rt":""},{"ar":"نَارَ","ur":"آگ ہے","hi":"आग है","ro":"aag hay","rt":""},{"ar":"جَهَنَّمَ","ur":"جہنم کی","hi":"जहन्नम की","ro":"jahannam ki","rt":""},{"ar":"خَٰلِدِينَ","ur":"ہمیشہ رہنے والے ہیں","hi":"हमेशा रहने वाले हैं","ro":"hamesha rehnay walay hain","rt":""},{"ar":"فِيهَآ","ur":"اس میں","hi":"उसमें","ro":"us mein","rt":""},{"ar":"أَبَدًا","ur":"ہمیشہ ہمیشہ","hi":"हमेशा-हमेशा","ro":"hamesha hamesha","rt":""}],"24":[{"ar":"حَتَّىٰٓ","ur":"یہاں تک کہ","hi":"यहाँ तक कि","ro":"yahan tak keh","rt":""},{"ar":"إِذَا","ur":"جب","hi":"जब","ro":"jab","rt":""},{"ar":"رَأَوۡاْ","ur":"وہ دیکھیں گے","hi":"वो देखेंगे","ro":"woh dekhein gay","rt":""},{"ar":"مَا","ur":"اسے جو","hi":"उसे जो","ro":"usay jo","rt":""},{"ar":"يُوعَدُونَ","ur":"وہ وعدہ کیے جاتے ہیں","hi":"वो वादा किए जाते हैं","ro":"woh wa’dah kiay jatay hain","rt":""},{"ar":"فَسَيَعۡلَمُونَ","ur":"تو عنقریب وہ جان لیں گے","hi":"तो अनक़रीब वो जान लेंगे","ro":"to anqarib woh jaan lein gay","rt":""},{"ar":"مَنۡ","ur":"کون","hi":"कौन","ro":"kon","rt":""},{"ar":"أَضۡعَفُ","ur":"زیادہ کمزور ہے","hi":"ज़्यादा कमज़ोर है","ro":"ziyadah kamzor hay","rt":""},{"ar":"نَاصِرًا","ur":"مددگار کے اعتبار سے","hi":"मददगार के ऐतबार से","ro":"madad gar kay i’tibar say","rt":""},{"ar":"وَأَقَلُّ","ur":"اور کون زیادہ کم ہے","hi":"और कौन ज़्यादा कम है","ro":"awr kon ziyadah kam hay","rt":"ق ل ل"},{"ar":"عَدَدًا","ur":"تعداد کے اعتبار سے","hi":"तादाद के ऐतबार से","ro":"ta’dad kay i’tibar say","rt":""}],"25":[{"ar":"قُلۡ","ur":"کہہ دیجیے","hi":"कह दीजिए","ro":"keh dijiay","rt":""},{"ar":"إِنۡ","ur":"نہیں","hi":"नहीं","ro":"nahin","rt":""},{"ar":"أَدۡرِيٓ","ur":"میں جانتا","hi":"मैं जानता","ro":"main janta","rt":""},{"ar":"أَقَرِيبٌ","ur":"کیا قریب ہے","hi":"क्या क़रीब है","ro":"keya qarib hay","rt":""},{"ar":"مَّا","ur":"وہ جو","hi":"वो जो","ro":"woh jo","rt":""},{"ar":"تُوعَدُونَ","ur":"تم وعدہ کیے جاتے ہو","hi":"तुम वादा किए जाते हो","ro":"tum wa’dah kiay jatay ho","rt":""},{"ar":"أَمۡ","ur":"یا","hi":"या","ro":"ya","rt":""},{"ar":"يَجۡعَلُ","ur":"مقرر کردے گا","hi":"मुक़र्रर कर देगा","ro":"muqarrar kar day ga","rt":""},{"ar":"لَهُۥ","ur":"اس کے لیے","hi":"उसके लिए","ro":"us kay liay","rt":""},{"ar":"رَبِّيٓ","ur":"میرا رب","hi":"मेरा रब","ro":"mera Rabb","rt":""},{"ar":"أَمَدًا","ur":"کوئی مدت","hi":"कोई मुद्दत","ro":"koi muddat","rt":""}],"26":[{"ar":"عَٰلِمُ","ur":"جاننے والا ہے","hi":"जानने वाला है","ro":"jannay wala hay","rt":""},{"ar":"ٱلۡغَيۡبِ","ur":"غیب کا","hi":"ग़ैब का","ro":"ghaib ka","rt":""},{"ar":"فَلَا","ur":"پس نہیں","hi":"पस नहीं","ro":"pas nahin","rt":""},{"ar":"يُظۡهِرُ","ur":"وہ ظاہر کرتا","hi":"वो ज़ाहिर करता","ro":"woh zahir karta","rt":"ظ ہ ر"},{"ar":"عَلَىٰ غَيۡبِهِۦٓ","ur":"اپنے غیب پر","hi":"अपने ग़ैब पर","ro":"apnay ghaib par","rt":"غ ی ب"},{"ar":"أَحَدًا","ur":"کسی ایک کو","hi":"किसी एक को","ro":"kisi aik ko","rt":""}],"27":[{"ar":"إِلَّا","ur":"مگر","hi":"मगर","ro":"magar","rt":""},{"ar":"مَنِ","ur":"جسے","hi":"जिसे","ro":"jisay","rt":""},{"ar":"ٱرۡتَضَىٰ","ur":"وہ پسند کرے","hi":"वो पसंद करे","ro":"woh pasand karay","rt":""},{"ar":"مِن رَّسُولٍ","ur":"کوئی رسول","hi":"कोई रसूल","ro":"koi rasul","rt":""},{"ar":"فَإِنَّهُۥ","ur":"پس بےشک وہ","hi":"पस बेशक वो","ro":"pas bayshak woh","rt":""},{"ar":"يَسۡلُكُ","ur":"وہ لگا دیتا ہے","hi":"वो लगा देता है","ro":"woh laga deta hay","rt":"س ل ک"},{"ar":"مِنۢ بَيۡنِ يَدَيۡهِ","ur":"اس کے آگے","hi":"उसके आगे","ro":"us kay aagay","rt":""},{"ar":"وَمِنۡ خَلۡفِهِۦ","ur":"اور اس کے پیچھے","hi":"और उसके पीछे","ro":"awr us kay peechhay","rt":""},{"ar":"رَصَدًا","ur":"محافظ","hi":"मुहाफ़िज़","ro":"Mohafiz","rt":"ر ص د"}],"28":[{"ar":"لِّيَعۡلَمَ","ur":"تاکہ وہ جان لے","hi":"ताकि वो जान ले","ro":"takeh woh jaan lay","rt":""},{"ar":"أَن","ur":"کہ","hi":"कि","ro":"keh","rt":""},{"ar":"قَدۡ","ur":"تحقیق","hi":"तहक़ीक़","ro":"tehqiq","rt":""},{"ar":"أَبۡلَغُواْ","ur":"انہوں نے پہنچا دئیے","hi":"उन्होंने पहुँचा दिए","ro":"unhon nay pahoncha diay","rt":"ب ل غ"},{"ar":"رِسَٰلَٰتِ","ur":"پیغامات","hi":"पैग़ामात","ro":"paeghamaat","rt":""},{"ar":"رَبِّهِمۡ","ur":"اپنے رب کے","hi":"अपने रब के","ro":"apnay Rabb kay","rt":""},{"ar":"وَأَحَاطَ","ur":"اور اس نے گھیر رکھا ہے","hi":"और उसने घेर रखा है","ro":"awr us nay gher rakhkha hay","rt":""},{"ar":"بِمَا","ur":"ان کو جو","hi":"उनको जो","ro":"un ko jo","rt":""},{"ar":"لَدَيۡهِمۡ","ur":"ان کے پاس ہے","hi":"उनके पास है","ro":"un kay paas hay","rt":""},{"ar":"وَأَحۡصَىٰ","ur":"اور اس نے شمار کررکھا ہے","hi":"और उसने शुमार कर रखा है","ro":"awr us nay shumar kar rakhkha hay","rt":"ح ص ی"},{"ar":"كُلَّ","ur":"ہر","hi":"हर","ro":"har","rt":""},{"ar":"شَيۡءٍ","ur":"چیز کو","hi":"चीज़ को","ro":"cheez ko","rt":""},{"ar":"عَدَدَۢا","ur":"عدد کے اعتبار سے","hi":"अदद के ऐतबार से","ro":"adad kay i’tibar say","rt":"ع د د"}]}