{"1":[{"ar":"يَٰٓأَيُّهَا","ur":"اے","hi":"ऐ","ro":"ay","rt":""},{"ar":"ٱلۡمُزَّمِّلُ","ur":"کپڑے میں لپٹنے والے","hi":"कपड़े में लिपटने वाले","ro":"kaprray mein lipatnay walay","rt":"ز م ل"}],"2":[{"ar":"قُمِ","ur":"قیام کیجیے","hi":"क़याम कीजिए","ro":"qiyam kijiay","rt":""},{"ar":"ٱلَّيۡلَ","ur":"رات کو","hi":"रात को","ro":"raat ko","rt":""},{"ar":"إِلَّا","ur":"مگر","hi":"मगर","ro":"magar","rt":""},{"ar":"قَلِيلًا","ur":"کم","hi":"कम","ro":"kam","rt":""}],"3":[{"ar":"نِّصۡفَهُۥٓ","ur":"آدھا اس کا","hi":"आधा उसका","ro":"aadha us ka","rt":""},{"ar":"أَوِ","ur":"یا","hi":"या","ro":"ya","rt":""},{"ar":"ٱنقُصۡ","ur":"کم کرلیجیے","hi":"कम कर लीजिए","ro":"kam kar lijiay","rt":"ن ق ص"},{"ar":"مِنۡهُ","ur":"اس سے","hi":"उससे","ro":"us say","rt":""},{"ar":"قَلِيلًا","ur":"تھوڑا سا","hi":"थोड़ा सा","ro":"thorra sa","rt":""}],"4":[{"ar":"أَوۡ","ur":"یا","hi":"या","ro":"ya","rt":""},{"ar":"زِدۡ","ur":"زیادہ بڑھادیجیے","hi":"ज़्यादा बढ़ा दीजिए","ro":"ziyadah barrha dijiay","rt":"ز ی د"},{"ar":"عَلَيۡهِ","ur":"اس پر","hi":"उस पर","ro":"us par","rt":""},{"ar":"وَرَتِّلِ","ur":"اورٹھہرٹھہرکر پڑھیے","hi":"और ठहर-ठहर कर पढ़िए","ro":"awr thahar thahar kar parrhiay","rt":"ر ت ل"},{"ar":"ٱلۡقُرۡءَانَ","ur":"قرآن کو","hi":"क़ुरआन को","ro":"Qur’an ko","rt":""},{"ar":"تَرۡتِيلًا","ur":"ٹھہر ٹھہر کر پڑھنا","hi":"ठहर-ठहर कर पढ़ना","ro":"thahar thahar kar parhna","rt":"ر ت ل"}],"5":[{"ar":"إِنَّا","ur":"بےشک ہم","hi":"बेशक हम","ro":"bayshak ham","rt":""},{"ar":"سَنُلۡقِي","ur":"عنقریب ہم ڈالیں گے","hi":"अनक़रीब हम डाल देंगे","ro":"bayshak ham daalein gay","rt":""},{"ar":"عَلَيۡكَ","ur":"آپ پر","hi":"आप पर","ro":"aap par","rt":""},{"ar":"قَوۡلًا","ur":"ایک بات/ قول","hi":"एक बात /क़ौल","ro":"aik baat/qawl","rt":""},{"ar":"ثَقِيلًا","ur":"بہت بھاری","hi":"बहुत भारी","ro":"bahot bhaari","rt":"ث ق ل"}],"6":[{"ar":"إِنَّ","ur":"بےشک","hi":"बेशक","ro":"bayshak","rt":""},{"ar":"نَاشِئَةَ","ur":"اٹھنا","hi":"उठना","ro":"uthna","rt":"ن ش أ"},{"ar":"ٱلَّيۡلِ","ur":"رات کا","hi":"रात का","ro":"raat ka","rt":""},{"ar":"هِيَ","ur":"وہ","hi":"वो","ro":"woh","rt":""},{"ar":"أَشَدُّ","ur":"زیادہ سخت ہے","hi":"ज़्यादा सख़्त है","ro":"ziyadah sakht hay","rt":""},{"ar":"وَطۡـًٔا","ur":"(نفس کو) روندنے میں","hi":"रौंदने में (नफ़्स को)","ro":"rondnay mein (nafs ko)","rt":"و ط أ"},{"ar":"وَأَقۡوَمُ","ur":"اور زیادہ درست ہے","hi":"और ज़्यादा दुरुस्त है","ro":"awr ziyadah durust hay","rt":""},{"ar":"قِيلًا","ur":"بات کرنے میں","hi":"बात करने में","ro":"baat karnay mein","rt":""}],"7":[{"ar":"إِنَّ","ur":"بےشک","hi":"बेशक","ro":"bayshak","rt":""},{"ar":"لَكَ","ur":"آپ کے لیے","hi":"आप के लिए","ro":"aap ka liay","rt":""},{"ar":"فِي ٱلنَّهَارِ","ur":"دن میں","hi":"दिन में","ro":"din mein","rt":""},{"ar":"سَبۡحًا","ur":"مصروفیت ہے","hi":"मसरूफ़ियत है","ro":"masrufiyat hay","rt":""},{"ar":"طَوِيلًا","ur":"طویل","hi":"तवील","ro":"taweel","rt":""}],"8":[{"ar":"وَٱذۡكُرِ","ur":"اور ذکر کیجیے","hi":"और ज़िक्र कीजिए","ro":"awr zikr kijiay","rt":""},{"ar":"ٱسۡمَ","ur":"نام","hi":"नाम","ro":"naam","rt":""},{"ar":"رَبِّكَ","ur":"اپنے رب کا","hi":"अपने रब का","ro":"apnay Rabb ka","rt":""},{"ar":"وَتَبَتَّلۡ","ur":"اور سب سے الگ ہوکر متوجہ ہو جایئے","hi":"और सबसे अलग हो कर मुतावज्जा हो जाइए","ro":"awr sab say alag ho kar mutawajjih ho ja’iay","rt":"ب ت ل"},{"ar":"إِلَيۡهِ","ur":"طرف اس کے","hi":"तरफ़ उसके","ro":"taraf us kay","rt":""},{"ar":"تَبۡتِيلًا","ur":"متوجہ ہونا","hi":"मुतावज्जा होना","ro":"mutawajjih hona","rt":"ب ت ل"}],"9":[{"ar":"رَّبُّ","ur":"رب","hi":"रब","ro":"Rabb","rt":""},{"ar":"ٱلۡمَشۡرِقِ","ur":"مشرق کا","hi":"मशरिक़ का","ro":"mashriq ka","rt":""},{"ar":"وَٱلۡمَغۡرِبِ","ur":"اور مغرب کا","hi":"और रब मग़रिब का","ro":"awr maghrib ka","rt":""},{"ar":"لَآ","ur":"نہیں","hi":"नहीं","ro":"nahin","rt":""},{"ar":"إِلَٰهَ","ur":"کوئی الٰہ (برحق)","hi":"कोई इलाह (बरहक़)","ro":"koi ilah (barhaq)","rt":""},{"ar":"إِلَّا","ur":"مگر","hi":"मगर","ro":"magar","rt":""},{"ar":"هُوَ","ur":"وہی","hi":"वो ही","ro":"wohi","rt":""},{"ar":"فَٱتَّخِذۡهُ","ur":"پس بنا لیجیے اسے","hi":"पस बना लीजिए उसे","ro":"pas bana lijiay usay","rt":""},{"ar":"وَكِيلًا","ur":"کارساز","hi":"कारसाज़","ro":"karsaz","rt":""}],"10":[{"ar":"وَٱصۡبِرۡ","ur":"اور صبر کیجیے","hi":"और सब्र कीजिए","ro":"awr sabr kijiay","rt":""},{"ar":"عَلَىٰ","ur":"اس پر","hi":"उस पर","ro":"us par","rt":""},{"ar":"مَا","ur":"جو","hi":"जो","ro":"jo","rt":""},{"ar":"يَقُولُونَ","ur":"وہ کہتے ہیں","hi":"वो कहते हैं","ro":"woh kehtay hain","rt":""},{"ar":"وَٱهۡجُرۡهُمۡ","ur":"اور چھوڑ دیجیے انہیں","hi":"और छोड़ दीजिए उन्हें","ro":"awr chhorr dijiay inhein","rt":"ہ ج ر"},{"ar":"هَجۡرًا","ur":"چھوڑنا","hi":"छोड़ना","ro":"chhorrna","rt":""},{"ar":"جَمِيلًا","ur":"خوب صورت (انداز میں)","hi":"ख़ूबसूरत(अंदाज़ में)","ro":"khubsurat (andaz mein)","rt":""}],"11":[{"ar":"وَذَرۡنِي","ur":"اور چھوڑ دیجیےمجھے","hi":"और छोड़ दीजिए मुझे","ro":"awr chhorr dijiay mujhay","rt":""},{"ar":"وَٱلۡمُكَذِّبِينَ","ur":"اور جھٹلانے والوں کو","hi":"और झुठलाने वालों को","ro":"awr jhutlanay walon ko","rt":""},{"ar":"أُوْلِي ٱلنَّعۡمَةِ","ur":"جو نعمتوں والے ہیں","hi":"जो नेअमतों वाले हैं","ro":"jo ne’maton walay hain","rt":""},{"ar":"وَمَهِّلۡهُمۡ","ur":"اور ڈھیل دیجیے انہیں","hi":"और ढील दीजिए उन्हें","ro":"awr dheel dijiay inhein","rt":"م ہ ل"},{"ar":"قَلِيلًا","ur":"تھوڑی سی","hi":"थोड़ी सी","ro":"thorri si","rt":""}],"12":[{"ar":"إِنَّ","ur":"بےشک","hi":"बेशक","ro":"bayshak","rt":""},{"ar":"لَدَيۡنَآ","ur":"ہمارے پاس","hi":"हमारे पास","ro":"hamaray paas","rt":""},{"ar":"أَنكَالًا","ur":"بیڑیاں ہیں","hi":"बेड़ियाँ हैं","ro":"bairriyan hain","rt":"ن ک ل"},{"ar":"وَجَحِيمًا","ur":"اور بھڑکتی آگ","hi":"और भड़कती आग","ro":"awr bharrakti aag","rt":""}],"13":[{"ar":"وَطَعَامًا","ur":"اور کھانا","hi":"और खाना","ro":"awr khana","rt":""},{"ar":"ذَاغُصَّةٍ","ur":"گلے میں اٹکنے والا","hi":"गले में अटकने वाला","ro":"galay mein ataknay wala","rt":"غ ص ص"},{"ar":"وَعَذَابًا","ur":"اور عذاب","hi":"और अज़ाब","ro":"awr azab","rt":""},{"ar":"أَلِيمًا","ur":"دردناک","hi":"दर्दनाक","ro":"dard nak","rt":""}],"14":[{"ar":"يَوۡمَ","ur":"جس دن","hi":"जिस दिन","ro":"jis din","rt":""},{"ar":"تَرۡجُفُ","ur":"کانپے گی","hi":"काँपेगी","ro":"kanpay gi","rt":"ر ج ف"},{"ar":"ٱلۡأَرۡضُ","ur":"زمین","hi":"ज़मीन","ro":"zamin","rt":""},{"ar":"وَٱلۡجِبَالُ","ur":"اور پہاڑ","hi":"और पहाड़","ro":"awr paharr","rt":""},{"ar":"وَكَانَتِ","ur":"اور ہوں گے","hi":"और होंगे","ro":"awr hon gay","rt":""},{"ar":"ٱلۡجِبَالُ","ur":"پہاڑ","hi":"पहाड़","ro":"paharr","rt":""},{"ar":"كَثِيبًا","ur":"ریت کے ٹیلے","hi":"रेत को टीले","ro":"rait kay teelay","rt":"ک ث ب"},{"ar":"مَّهِيلًا","ur":"بکھرے ہوئے","hi":"बिखरे हुए","ro":"bikhray huay","rt":"ہ ی ل"}],"15":[{"ar":"إِنَّآ","ur":"بےشک ہم","hi":"बेशक हम","ro":"bayshak ham","rt":""},{"ar":"أَرۡسَلۡنَآ","ur":"بھیجا ہم نے","hi":"भेजा हमने","ro":"bheja ham nay","rt":""},{"ar":"إِلَيۡكُمۡ","ur":"طرف آپ کے","hi":"तरफ़ आपके","ro":"taraf aap kay","rt":""},{"ar":"رَسُولًا","ur":"ایک رسول","hi":"एक रसूल","ro":"aik Rasul","rt":""},{"ar":"شَٰهِدًا","ur":"گواہ","hi":"गवाह","ro":"gawah","rt":""},{"ar":"عَلَيۡكُمۡ","ur":"تم پر","hi":"तुम पर","ro":"tum par","rt":""},{"ar":"كَمَآ","ur":"جیسا کہ","hi":"जैसा कि","ro":"jaisa keh","rt":""},{"ar":"أَرۡسَلۡنَآ","ur":"بھیجا ہم نے","hi":"भेजा हमने","ro":"bheja ham nay","rt":""},{"ar":"إِلَىٰ فِرۡعَوۡنَ","ur":"طرف فرعون کے","hi":"तरफ़ फ़िरऔन के","ro":"taraf Fir’awn kay","rt":""},{"ar":"رَسُولًا","ur":"ایک رسول","hi":"एक रसूल","ro":"aik Rasul","rt":""}],"16":[{"ar":"فَعَصَىٰ","ur":"تو نافرمانی کی","hi":"तो नाफ़रमानी की","ro":"to na farmani ki","rt":""},{"ar":"فِرۡعَوۡنُ","ur":"فرعون نے","hi":"फ़िरऔन ने","ro":"Fir’awn nay","rt":""},{"ar":"ٱلرَّسُولَ","ur":"اس رسول کی","hi":"उस रसूल की","ro":"us Rasul ki","rt":""},{"ar":"فَأَخَذۡنَٰهُ","ur":"تو پکڑ لیا ہم نے اسے","hi":"तो पकड़ लिया हमने उसे","ro":"to pakarr liya ham nay usay","rt":""},{"ar":"أَخۡذًا","ur":"پکڑنا","hi":"पकड़ना","ro":"pakarrna","rt":""},{"ar":"وَبِيلًا","ur":"سخت","hi":"सख़्त","ro":"sakht","rt":"و ب ل"}],"17":[{"ar":"فَكَيۡفَ","ur":"تو کس طرح","hi":"तो किस तरह","ro":"to kis tarah","rt":""},{"ar":"تَتَّقُونَ","ur":"تم بچو گے","hi":"तुम बचोगे","ro":"tum bacho gay","rt":""},{"ar":"إِن","ur":"اگر","hi":"अगर","ro":"agar","rt":""},{"ar":"كَفَرۡتُمۡ","ur":"کفر کیا تم نے","hi":"कुफ़्र किया तुमने","ro":"kufr kiya tum nay","rt":""},{"ar":"يَوۡمًا","ur":"اس دن سے","hi":"उस दिन से","ro":"us din say","rt":""},{"ar":"يَجۡعَلُ","ur":"جو کر دے گا","hi":"जो कर देगा","ro":"jo kar day ga","rt":""},{"ar":"ٱلۡوِلۡدَٰنَ","ur":"بچوں کو","hi":"बच्चों को","ro":"bachchon ko","rt":""},{"ar":"شِيبًا","ur":"بوڑھا","hi":"बूढ़ा","ro":"boorrha","rt":"ش ی ب"}],"18":[{"ar":"ٱلسَّمَآءُ","ur":"آسمان","hi":"आसमान","ro":"aasman","rt":""},{"ar":"مُنفَطِرُۢ","ur":"پھٹ جانے والا ہوگا","hi":"फट जाने वाला होगा","ro":"phat janay wala ho ga","rt":"ف ط ر"},{"ar":"بِهِۦۚ","ur":"اس میں","hi":"उसमें","ro":"us mein","rt":""},{"ar":"كَانَ","ur":"ہے","hi":"है","ro":"hay","rt":""},{"ar":"وَعۡدُهُۥ","ur":"وعدہ اس کا","hi":"वादा उसका","ro":"wa’dah us ka","rt":""},{"ar":"مَفۡعُولًا","ur":"ہو کر رہنے والا","hi":"हो कर रहने वाला","ro":"ho kar rehnay wala","rt":""}],"19":[{"ar":"إِنَّ","ur":"بےشک","hi":"बेशक","ro":"bayshak","rt":""},{"ar":"هَٰذِهِۦ","ur":"یہ","hi":"ये","ro":"yeh","rt":""},{"ar":"تَذۡكِرَةٌۖ","ur":"ایک نصیحت ہے","hi":"एक नसीहत है","ro":"aik nasihat hay","rt":""},{"ar":"فَمَن","ur":"پس جو کوئی","hi":"पस जो कोई","ro":"pas jo koi","rt":""},{"ar":"شَآءَ","ur":"چاہے","hi":"चाहे","ro":"chahay","rt":""},{"ar":"ٱتَّخَذَ","ur":"بنالے","hi":"बना ले","ro":"bana lay","rt":""},{"ar":"إِلَىٰ رَبِّهِۦ","ur":"طرف اپنے رب کے","hi":"तरफ़ अपने रब के","ro":"taraf apnay Rabb kay","rt":""},{"ar":"سَبِيلًا","ur":"راستہ","hi":"रास्ता","ro":"rastah","rt":""}],"20":[{"ar":"إِنَّ","ur":"بےشک","hi":"बेशक","ro":"bayshak","rt":""},{"ar":"رَبَّكَ","ur":"رب آپ کا","hi":"रब आपका","ro":"Rabb aap ka","rt":""},{"ar":"يَعۡلَمُ","ur":"وہ جانتا ہے","hi":"वो जानता है","ro":"woh janta hay","rt":""},{"ar":"أَنَّكَ","ur":"بےشک آپ","hi":"बेशक आप","ro":"bayshak aap","rt":""},{"ar":"تَقُومُ","ur":"آپ قیام کرتے ہیں","hi":"आप क़याम करते हैं","ro":"aap giyam kartay hain","rt":""},{"ar":"أَدۡنَىٰ","ur":"قریب","hi":"क़रीब","ro":"qarib","rt":""},{"ar":"مِن ثُلُثَيِ","ur":"دو تہائی","hi":"दो तिहाई","ro":"do tihai","rt":""},{"ar":"ٱلَّيۡلِ","ur":"رات کا","hi":"रात का","ro":"raat ka","rt":""},{"ar":"وَنِصۡفَهُۥ","ur":"اور (کبھی) نصف اس کا","hi":"और (कभी)निस्फ़ उसका","ro":"awr (kabhi) nisf us ka","rt":""},{"ar":"وَثُلُثَهُۥ","ur":"اور ایک تہائی اس کا","hi":"और एक तिहाई उसका","ro":"awr aik tihai us ka","rt":""},{"ar":"وَطَآئِفَةٌ","ur":"اور ایک گروہ","hi":"और एक गिरोह","ro":"awr aik goroh","rt":""},{"ar":"مِّنَ ٱلَّذِينَ","ur":"ان لوگوں میں سے جو","hi":"उन लोगों में से जो","ro":"un logon mein say jo","rt":""},{"ar":"مَعَكَۚ","ur":"آپ کے ساتھ ہیں","hi":"आपके साथ हैं","ro":"aap kay sath hain","rt":""},{"ar":"وَٱللَّهُ","ur":"اور اللہ","hi":"और अल्लाह","ro":"awr Allah","rt":""},{"ar":"يُقَدِّرُ","ur":"وہ اندازہ رکھتا ہے","hi":"वो अंदाज़ा रखता है","ro":"woh andazah rakhta hay","rt":""},{"ar":"ٱلَّيۡلَ","ur":"رات کا","hi":"रात का","ro":"raat ka","rt":""},{"ar":"وَٱلنَّهَارَۚ","ur":"اور دن کا","hi":"और दिन का","ro":"awr din ka","rt":""},{"ar":"عَلِمَ","ur":"وہ جانتا ہے","hi":"वो जानता है","ro":"woh janta hay","rt":""},{"ar":"أَن","ur":"کہ","hi":"कि","ro":"keh","rt":""},{"ar":"لَّن","ur":"ہرگز نہ","hi":"हरगिज़ ना","ro":"hargiz nah","rt":""},{"ar":"تُحۡصُوهُ","ur":"تم شمار کرسکو گے اسے","hi":"तुम शुमार कर सकोगे उसे","ro":"tum shumar kar sako gay usay","rt":"ح ص ی"},{"ar":"فَتَابَ","ur":"تو وہ مہربان ہوا","hi":"तो वो मेहरबान हुआ","ro":"to woh mehrban hua","rt":""},{"ar":"عَلَيۡكُمۡۖ","ur":"تم پر","hi":"तुम पर","ro":"tum par","rt":""},{"ar":"فَٱقۡرَءُواْ","ur":"پس پڑھو","hi":"पस पढ़ो","ro":"pas parrho","rt":""},{"ar":"مَا","ur":"جو","hi":"जो","ro":"jo","rt":""},{"ar":"تَيَسَّرَ","ur":"میسر آئے","hi":"मयस्सर आए","ro":"muyassar aa’ay","rt":""},{"ar":"مِنَ ٱلۡقُرۡءَانِۚ","ur":"قرآن میں سے","hi":"क़ुरआन में से","ro":"Qur'an mein say","rt":""},{"ar":"عَلِمَ","ur":"وہ جانتا ہے","hi":"वो जानता है","ro":"woh janta hay","rt":""},{"ar":"أَن","ur":"کہ","hi":"कि","ro":"keh","rt":""},{"ar":"سَيَكُونُ","ur":"عنقریب ہوں گے","hi":"अनक़रीब होंगे","ro":"anqarib hon gay","rt":""},{"ar":"مِنكُم","ur":"تم میں","hi":"तुम में","ro":"tum mein","rt":""},{"ar":"مَّرۡضَىٰ","ur":"بیمار","hi":"बीमार","ro":"bimar","rt":""},{"ar":"وَءَاخَرُونَ","ur":"اور کچھ دوسرے","hi":"और कुछ दूसरे","ro":"awr kuchh dusray","rt":""},{"ar":"يَضۡرِبُونَ","ur":"جوسفر کرتے ہوں گے","hi":"जो सफ़र करते होंगे","ro":"jo safar kartay hon gay","rt":""},{"ar":"فِي ٱلۡأَرۡضِ","ur":"زمین میں","hi":"ज़मीन में","ro":"zamin mein","rt":""},{"ar":"يَبۡتَغُونَ","ur":"وہ تلاش کرتے ہوں گے","hi":"वो तलाश करते होंगे","ro":"woh talash kartay hon gay","rt":""},{"ar":"مِن فَضۡلِ","ur":"فضل میں سے","hi":"फ़ज़ल में से","ro":"fazl mein say","rt":""},{"ar":"ٱللَّهِ","ur":"اللہ کے","hi":"अल्लाह के","ro":"Allah kay","rt":""},{"ar":"وَءَاخَرُونَ","ur":"اور کچھ دوسرے","hi":"और कुछ दूसरे","ro":"awr kuchh dusray","rt":""},{"ar":"يُقَٰتِلُونَ","ur":"جو جنگ کرتے ہوں گے","hi":"जो जंग करते होंगे","ro":"jo jang kartay hon gay","rt":""},{"ar":"فِي سَبِيلِ ٱللَّهِۖ","ur":"اللہ کے راستے میں","hi":"अल्लाह के रास्ते में","ro":"Allah kay rastay mein","rt":""},{"ar":"فَٱقۡرَءُواْ","ur":"پس پڑھو","hi":"पस पढ़ो","ro":"pas parrho","rt":""},{"ar":"مَا","ur":"جو","hi":"जो","ro":"jo","rt":""},{"ar":"تَيَسَّرَ","ur":"میسر آئے","hi":"मयस्सर आए","ro":"muyassar aa’ay","rt":""},{"ar":"مِنۡهُۚ","ur":"اس میں سے","hi":"उसमें से","ro":"us mein say","rt":""},{"ar":"وَأَقِيمُواْ","ur":"اور قائم کرو","hi":"और क़ायम करो","ro":"awr qa’im karo","rt":""},{"ar":"ٱلصَّلَوٰةَ","ur":"نماز","hi":"नमाज़","ro":"namaz","rt":""},{"ar":"وَءَاتُواْ","ur":"اور ادا کرو","hi":"और अदा करो","ro":"awr adaa karo","rt":""},{"ar":"ٱلزَّكَوٰةَ","ur":"زکوٰۃ","hi":"ज़कात","ro":"zakat","rt":""},{"ar":"وَأَقۡرِضُواْ","ur":"اور قرض دو","hi":"और क़र्ज़ दो","ro":"awr qarz do","rt":""},{"ar":"ٱللَّهَ","ur":"اللہ کو","hi":"अल्लाह को","ro":"Allah ko","rt":""},{"ar":"قَرۡضًا","ur":"قرض","hi":"क़र्ज़","ro":"qarz","rt":""},{"ar":"حَسَنًاۚ","ur":"اچھا","hi":"अच्छा","ro":"achcha","rt":""},{"ar":"وَمَا","ur":"اور جو","hi":"और जो","ro":"awr jo","rt":""},{"ar":"تُقَدِّمُواْ","ur":"تم آگے بھیجو گے","hi":"तुम आगे भेजोगे","ro":"tum aagay bhejo gay","rt":"ق د م"},{"ar":"لِأَنفُسِكُم","ur":"اپنے نفسوں کے لیے","hi":"अपने नफ़्सों के लिए","ro":"apnay nafson kay liay","rt":""},{"ar":"مِّنۡ خَيۡرٍ","ur":"کوئی بھلائی","hi":"कोई भलाई","ro":"koi bhalai","rt":""},{"ar":"تَجِدُوهُ","ur":"تم پالو گے اسے","hi":"तुम पा लोगे उसे","ro":"tum pa lo gay usay","rt":""},{"ar":"عِندَ","ur":"پاس","hi":"पास","ro":"paas","rt":""},{"ar":"ٱللَّهِ","ur":"اللہ کے","hi":"अल्लाह के","ro":"Allah kay","rt":""},{"ar":"هُوَ","ur":"وہ","hi":"वो","ro":"woh","rt":""},{"ar":"خَيۡرًا","ur":"بہتر ہے","hi":"बेहतर है","ro":"behtar hay","rt":""},{"ar":"وَأَعۡظَمَ","ur":"اور زیادہ بڑا ہے","hi":"और ज़्यादा बड़ा है","ro":"awr ziyadah barra hay","rt":""},{"ar":"أَجۡرًاۚ","ur":"اجر میں","hi":"अजर में","ro":"ajr mein","rt":""},{"ar":"وَٱسۡتَغۡفِرُواْ","ur":"اور بخشش مانگو","hi":"और बख़्शिश माँगो","ro":"awr bakhshish mango","rt":""},{"ar":"ٱللَّهَۖ","ur":"اللہ سے","hi":"अल्लाह से","ro":"Allah say","rt":""},{"ar":"إِنَّ","ur":"بےشک","hi":"बेशक","ro":"bayshak","rt":""},{"ar":"ٱللَّهَ","ur":"اللہ","hi":"अल्लाह","ro":"Allah","rt":""},{"ar":"غَفُورٌ","ur":"بہت بخشنے والا ہے","hi":"बहुत बख़्शने वाला है","ro":"bahot bakhshnay wala hay","rt":""},{"ar":"رَّحِيمُۢ","ur":"نہایت رحم کرنے والا ہے","hi":"निहायत रहम करने वाला है","ro":"nihayat rehm karnay wala hay","rt":""}]}