{"1":[{"ar":"إِذَا","ur":"جب","hi":"जब","ro":"jab","rt":""},{"ar":"ٱلسَّمَآءُ","ur":"آسمان","hi":"आसमान","ro":"aasman","rt":""},{"ar":"ٱنشَقَّتۡ","ur":"پھٹ جائے گا","hi":"फट जाऐगा","ro":"phat ja’ay ga","rt":"ش ق ق"}],"2":[{"ar":"وَأَذِنَتۡ","ur":"اوروہ کان لگائے ہوئے ہے","hi":"और वो कान लगाए हुए है","ro":"awr woh kaan\nlaga’ay huay hay","rt":"أ ذ ن"},{"ar":"لِرَبِّهَا","ur":"اپنے رب کے لیے","hi":"अपने रब के लिए","ro":"apnay Rabb kay liay","rt":""},{"ar":"وَحُقَّتۡ","ur":"اور وہ حق دیا گیا ہے","hi":"और वो हक़ दिया गया है","ro":"awr woh haq diya gaya hay","rt":"ح ق ق"}],"3":[{"ar":"وَإِذَا","ur":"اور جب","hi":"और जब","ro":"awr jab","rt":""},{"ar":"ٱلۡأَرۡضُ","ur":"زمین","hi":"ज़मीन","ro":"zamin","rt":""},{"ar":"مُدَّتۡ","ur":"پھیلادی جائے گی","hi":"फैला दी जाएगी","ro":"phaila di\nja’ay gi","rt":"م د د"}],"4":[{"ar":"وَأَلۡقَتۡ","ur":"اور وہ ڈال دے گی","hi":"और वो डाल देगी","ro":"awr woh daal day gi","rt":""},{"ar":"مَا","ur":"جو کچھ","hi":"जो कुछ","ro":"jo kuchh","rt":""},{"ar":"فِيهَا","ur":"اس میں ہے","hi":"उसमें है","ro":"us mein hay","rt":""},{"ar":"وَتَخَلَّتۡ","ur":"اوروہ خالی ہو جائے گی","hi":"और वो ख़ाली हो जाएगी","ro":"awr woh khali ho ja’ay gi","rt":""}],"5":[{"ar":"وَأَذِنَتۡ","ur":"اور وہ کان لگائے ہوئے ہے","hi":"और वो कान लगाए हुए है","ro":"awr woh kaan laga’ay huay hay","rt":""},{"ar":"لِرَبِّهَا","ur":"اپنے رب کے لیے","hi":"अपने रब के लिए","ro":"apnay Rabb kay liay","rt":""},{"ar":"وَحُقَّتۡ","ur":"اور وہ حق دی گئی ہے","hi":"और वो हक़ दी गई है","ro":"awr woh haq di gai hay","rt":""}],"6":[{"ar":"يَٰٓأَيُّهَا","ur":"اے","hi":"ऐ","ro":"ay","rt":""},{"ar":"ٱلۡإِنسَٰنُ","ur":"انسان","hi":"इन्सान","ro":"insan","rt":""},{"ar":"إِنَّكَ","ur":"بےشک تو","hi":"बेशक तू","ro":"bayshak tu","rt":""},{"ar":"كَادِحٌ","ur":"محنت کرنے والا ہے","hi":"मेहनत करने वाला है","ro":"mehnat karnay wala hay","rt":"ک د ح"},{"ar":"إِلَىٰ رَبِّكَ","ur":"طرف اپنے رب کے","hi":"तरफ़ अपने रब के","ro":"taraf apnay Rabb kay","rt":""},{"ar":"كَدۡحًا","ur":"سخت محنت","hi":"सख़्त मेहनत","ro":"sakht mehnat","rt":""},{"ar":"فَمُلَٰقِيهِ","ur":"پھر ملنے والا ہے اس سے","hi":"फिर मिलने वाला है उससे","ro":"phir milnay wala hay us say","rt":"ل ق ی"}],"7":[{"ar":"فَأَمَّا","ur":"تو رہا","hi":"तो रहा","ro":"to raha","rt":""},{"ar":"مَنۡ","ur":"وہ جو","hi":"वो जो","ro":"woh jo","rt":""},{"ar":"أُوتِيَ","ur":"دیا گیا","hi":"दिया गया","ro":"diya gaya","rt":""},{"ar":"كِتَٰبَهُۥ","ur":"کتاب اپنی","hi":"किताब अपनी","ro":"kitab apni","rt":""},{"ar":"بِيَمِينِهِۦ","ur":"اپنے دائیں ہاتھ میں","hi":"अपने दाऐं हाथ में","ro":"apnay da’ein hath mein","rt":""}],"8":[{"ar":"فَسَوۡفَ","ur":"توعنقریب","hi":"तो अनक़रीब","ro":"to anqarib","rt":""},{"ar":"يُحَاسَبُ","ur":"وہ حساب لیا جائے گا","hi":"वो हिसाब लिया जाएग","ro":"woh hisab liya ja’ay ga","rt":"ح س ب"},{"ar":"حِسَابًا","ur":"حساب","hi":"हिसाब","ro":"hisab","rt":""},{"ar":"يَسِيرًا","ur":"نہایت آسان","hi":"निहायत आसान","ro":"nihayat aasan","rt":"ی س ر"}],"9":[{"ar":"وَيَنقَلِبُ","ur":"اور وہ لوٹے گا","hi":"और वो लौटेगा","ro":"awr woh lawtay ga","rt":""},{"ar":"إِلَىٰٓ أَهۡلِهِۦ","ur":"طرف اپنے گھر والوں کے","hi":"तरफ़ अपने घर वालों के","ro":"taraf apnay ghar walon kay","rt":""},{"ar":"مَسۡرُورًا","ur":"مسرور/خوش","hi":"मसरूर/ ख़ुश","ro":"masrur/khush","rt":"س ر ر"}],"10":[{"ar":"وَأَمَّا","ur":"اور رہا","hi":"और रहा","ro":"awr raha","rt":""},{"ar":"مَنۡ","ur":"وہ جو","hi":"वो जो","ro":"woh jo","rt":""},{"ar":"أُوتِيَ","ur":"دیا گیا","hi":"दिया गया","ro":"diya gaya","rt":""},{"ar":"كِتَٰبَهُۥ","ur":"کتاب اپنی","hi":"किताब अपनी","ro":"kitab apni","rt":""},{"ar":"وَرَآءَ","ur":"پیچھے","hi":"पीछे से","ro":"peechhay","rt":""},{"ar":"ظَهۡرِهِۦ","ur":"اپنی پشت کے","hi":"अपनी पुश्त के","ro":"apni pusht kay","rt":"ظ ہ ر"}],"11":[{"ar":"فَسَوۡفَ","ur":"تو عنقریب","hi":"तो अनक़रीब","ro":"to anqarib","rt":""},{"ar":"يَدۡعُواْ","ur":"وہ پکارے گا","hi":"वो पुकारेगा","ro":"woh pukaray ga","rt":""},{"ar":"ثُبُورًا","ur":"ہلاکت کو","hi":"हलाकत को","ro":"halakat ko","rt":"ث ب ر"}],"12":[{"ar":"وَيَصۡلَىٰ","ur":"اور وہ جلے گا","hi":"और वो जलेगा","ro":"awr woh jalay ga","rt":"ص ل ی"},{"ar":"سَعِيرًا","ur":"بھڑکتی آگ میں","hi":"भड़कती आग में","ro":"bharrakti aag mein","rt":""}],"13":[{"ar":"إِنَّهُۥ","ur":"بےشک وہ","hi":"बेशक वो","ro":"bayshak woh","rt":""},{"ar":"كَانَ","ur":"تھا وہ","hi":"था वो","ro":"tha woh","rt":""},{"ar":"فِيٓ أَهۡلِهِۦ","ur":"اپنے گھر والوں میں","hi":"अपने घर वालों में","ro":"apnay ghar walon mein","rt":""},{"ar":"مَسۡرُورًا","ur":"مسرور/ خوش","hi":"मसरूर /ख़ुश","ro":"masrur/khush","rt":""}],"14":[{"ar":"إِنَّهُۥ","ur":"بےشک وہ","hi":"बेशक वो","ro":"bayshak woh","rt":""},{"ar":"ظَنَّ","ur":"وہ سمجھتا تھا","hi":"वो समझता था","ro":"woh samajhta tha","rt":""},{"ar":"أَن","ur":"کہ","hi":"कि","ro":"keh","rt":""},{"ar":"لَّن","ur":"ہرگز نہیں","hi":"हरगिज़ नहीं","ro":"hargiz nahin","rt":""},{"ar":"يَحُورَ","ur":"وہ لوٹے گا","hi":"वो लौटेगा","ro":"woh lawtay ga","rt":"ح و ر"}],"15":[{"ar":"بَلَىٰٓۚ","ur":"کیوں نہیں","hi":"क्यों नहीं","ro":"kiun nahin","rt":""},{"ar":"إِنَّ","ur":"بےشک","hi":"बेशक","ro":"bayshak","rt":""},{"ar":"رَبَّهُۥ","ur":"رب اس کا","hi":"रब उसका","ro":"Rabb us ka","rt":""},{"ar":"كَانَ","ur":"تھا","hi":"था","ro":"tha","rt":""},{"ar":"بِهِۦ","ur":"اسے","hi":"उसे","ro":"usay","rt":""},{"ar":"بَصِيرًا","ur":"خوب دیکھنے والا","hi":"ख़ूब देखने वाला","ro":"khub dekhnay wala","rt":""}],"16":[{"ar":"فَلَآ","ur":"پس نہیں","hi":"पस नहीं","ro":"pas nahin","rt":""},{"ar":"أُقۡسِمُ","ur":"میں قسم کھاتا ہوں","hi":"मैं क़सम खाता हूँ","ro":"main qasam khata hun","rt":""},{"ar":"بِٱلشَّفَقِ","ur":"شفق کی","hi":"शफ़क़ की","ro":"shafaq ki","rt":"ش ف ق"}],"17":[{"ar":"وَٱلَّيۡلِ","ur":"اور رات کی","hi":"और रात की","ro":"awr raat ki","rt":""},{"ar":"وَمَا","ur":"اور اس کی جسے","hi":"और उसकी जिसे","ro":"awr us ki jisay","rt":""},{"ar":"وَسَقَ","ur":"وہ سمیٹ لے","hi":"वो समेट ले","ro":"woh samait lay","rt":"و س ق"}],"18":[{"ar":"وَٱلۡقَمَرِ","ur":"اور چاند کی","hi":"और चाँद की","ro":"awr chaand ki","rt":""},{"ar":"إِذَا","ur":"جب","hi":"जब","ro":"jab","rt":""},{"ar":"ٱتَّسَقَ","ur":"وہ پورا ہوجائے","hi":"वो पूरा हो जाए","ro":"woh poora ho ja’ay","rt":"و س ق"}],"19":[{"ar":"لَتَرۡكَبُنَّ","ur":"البتہ تم ضرورچڑھتے جاؤگے","hi":"अलबत्ता तुम ज़रूर चढ़ते जाओगे","ro":"albattah tum zarur charrhtay jao gay","rt":"ر ک ب"},{"ar":"طَبَقًا","ur":"ایک درجہ کو","hi":"एक दर्जे को","ro":"aik darjah ko","rt":""},{"ar":"عَن طَبَقٍ","ur":"دوسرے درجے سے","hi":"दूसरे दर्जे से","ro":"dusray darjay ko","rt":"ط ب ق"}],"20":[{"ar":"فَمَا","ur":"پس کیا ہے","hi":"पस क्या है","ro":"pas keya hay","rt":""},{"ar":"لَهُمۡ","ur":"انہیں","hi":"उन्हें","ro":"inhein","rt":""},{"ar":"لَا يُؤۡمِنُونَ","ur":"نہیں وہ ایمان لاتے","hi":"नहीं वो ईमान लाते","ro":"nahin woh iman latay","rt":""}],"21":[{"ar":"وَإِذَا","ur":"اور جب","hi":"और जब","ro":"awr jab","rt":""},{"ar":"قُرِئَ","ur":"پڑھا جاتا ہے","hi":"पढ़ा जाता है","ro":"parrha jata hay","rt":"ق ر أ"},{"ar":"عَلَيۡهِمُ","ur":"ان پر","hi":"उन पर","ro":"in par","rt":""},{"ar":"ٱلۡقُرۡءَانُ","ur":"قرآن","hi":"क़ुरआन","ro":"Qur’an","rt":""},{"ar":"لَا يَسۡجُدُونَۤ۩","ur":"نہیں وہ سجدہ کرتے","hi":"नहीं वो सजदा करते","ro":"nahin woh sajdah karta","rt":""}],"22":[{"ar":"بَلِ","ur":"بلکہ","hi":"बल्कि","ro":"balkeh","rt":""},{"ar":"ٱلَّذِينَ","ur":"وہ لوگ جنہوں نے","hi":"वो लोग जिन्होंने","ro":"woh log jinhon nay","rt":""},{"ar":"كَفَرُواْ","ur":"کفر کیا","hi":"कुफ़्र किया","ro":"kufr kiya","rt":""},{"ar":"يُكَذِّبُونَ","ur":"وہ جھٹلاتے ہیں","hi":"वो झुठलाते हैं","ro":"woh jhutlatay hain","rt":""}],"23":[{"ar":"وَٱللَّهُ","ur":"اور اللہ","hi":"और अल्लाह","ro":"awr Allah","rt":""},{"ar":"أَعۡلَمُ","ur":"خوب جانتا ہے","hi":"ख़ूब जानता है","ro":"khub janta hay","rt":""},{"ar":"بِمَا","ur":"اسے جو","hi":"उसे जो","ro":"usay jo","rt":""},{"ar":"يُوعُونَ","ur":"وہ سمیٹ رہے ہیں","hi":"वो समेट रहे हैं","ro":"woh samait rahay hain","rt":"و ع ی"}],"24":[{"ar":"فَبَشِّرۡهُم","ur":"پس خوش خبری دے دیجیے انہیں","hi":"पस ख़ुशख़बरी दे दीजिए उन्हें","ro":"pas khush khabri day dijiay inhein","rt":""},{"ar":"بِعَذَابٍ","ur":"عذاب","hi":"अज़ाब की","ro":"azab","rt":""},{"ar":"أَلِيمٍ","ur":"دردناک کی","hi":"दर्दनाक","ro":"dard nak ki","rt":""}],"25":[{"ar":"إِلَّا","ur":"سوائے","hi":"सिवाए","ro":"siwa’ay","rt":""},{"ar":"ٱلَّذِينَ","ur":"ان لوگوں کے جو","hi":"उन लोगों के जो","ro":"un logon kay jo","rt":""},{"ar":"ءَامَنُواْ","ur":"ایمان لائے","hi":"ईमान लाए","ro":"iman la’ay","rt":""},{"ar":"وَعَمِلُواْ","ur":"اور انہوں نے عمل کیے","hi":"और उन्होंने अमल किए","ro":"awr unhon nay amal kiay","rt":""},{"ar":"ٱلصَّٰلِحَٰتِ","ur":"نیک","hi":"नेक","ro":"nek","rt":""},{"ar":"لَهُمۡ","ur":"ان کے لیے","hi":"उनके लिए","ro":"un kay liay","rt":""},{"ar":"أَجۡرٌ","ur":"اجر ہے","hi":"अजर है","ro":"ajr hay","rt":""},{"ar":"غَيۡرُ","ur":"نہ","hi":"ना","ro":"nah","rt":""},{"ar":"مَمۡنُونِۢ","ur":"ختم ہونے والا","hi":"ख़त्म होने वाला","ro":"khatm honay wala","rt":"م ن ن"}]}